setup.py
pristine/__init__.py
pristine.egg-info/PKG-INFO
pristine.egg-info/SOURCES.txt
pristine.egg-info/dependency_links.txt
pristine.egg-info/not-zip-safe
pristine.egg-info/requires.txt
pristine.egg-info/top_level.txt