Metadata-Version: 1.0
Name: pristine
Version: 0.1
Summary: My own take on the obvious architecture
Home-page: To be determined
Author: JoeDRL
Author-email: joe.desruisseaux.langlois@gmail.com
License: LGPL
Platform: UNKNOWN
